{"type":"Topology","arcs":[[[175,287],[-6,-63]],[[169,224],[-23,-77]],[[146,147],[-33,-24]],[[113,123],[-1,28]],[[112,151],[69,236]],[[181,387],[-6,-100]],[[269,313],[-35,-9]],[[234,304],[-2,78]],[[232,382],[120,40]],[[352,422],[-83,-109]],[[232,152],[-57,-61]],[[175,91],[-3,5]],[[172,96],[-12,24]],[[160,120],[-14,27]],[[146,147],[86,70]],[[232,217],[0,-65]],[[55,0],[83,28]],[[138,28],[-83,-28]],[[270,271],[-101,-47]],[[175,287],[59,17]],[[269,313],[1,-42]],[[181,387],[51,40]],[[232,427],[0,-45]],[[172,96],[-138,-54]],[[34,42],[-12,28]],[[22,70],[138,50]],[[175,91],[18,-27]],[[193,64],[-55,-36]],[[55,0],[-21,42]],[[22,70],[-22,29]],[[0,99],[113,24]],[[0,99],[112,52]],[[270,271],[-38,-54]],[[232,152],[-39,-88]],[[232,427],[120,-5]]],"transform":{"scale":[0.00018562099147729165,0.00015148340281019218],"translate":[124.42613673400004,6.854157110000075]},"objects":{"bgysubmuns-municity-1908820000":{"type":"GeometryCollection","geometries":[{"arcs":[[0,1,2,3,4,5]],"type":"Polygon","properties":{"adm1_psgc":1900000000,"adm2_psgc":1908800000,"adm3_psgc":1908820000,"adm4_psgc":1908820001,"adm4_en":"Bagong","geo_level":"Bgy","len_crs":10210,"area_crs":4165364,"len_km":10,"area_km2":4},"id":1908820001},{"arcs":[[6,7,8,9]],"type":"Polygon","properties":{"adm1_psgc":1900000000,"adm2_psgc":1908800000,"adm3_psgc":1908820000,"adm4_psgc":1908820002,"adm4_en":"Bialong","geo_level":"Bgy","len_crs":8130,"area_crs":3714063,"len_km":8,"area_km2":3},"id":1908820002},{"arcs":[[10,11,12,13,14,15]],"type":"Polygon","properties":{"adm1_psgc":1900000000,"adm2_psgc":1908800000,"adm3_psgc":1908820000,"adm4_psgc":1908820003,"adm4_en":"Kuloy","geo_level":"Bgy","len_crs":6035,"area_crs":1993238,"len_km":6,"area_km2":1},"id":1908820003},{"arcs":[[16,17]],"type":"Polygon","properties":{"adm1_psgc":1900000000,"adm2_psgc":1908800000,"adm3_psgc":1908820000,"adm4_psgc":1908820004,"adm4_en":"Labu-labu","geo_level":"Bgy","len_crs":6181,"area_crs":1941151,"len_km":6,"area_km2":1},"id":1908820004},{"arcs":[[18,-1,19,-7,20]],"type":"Polygon","properties":{"adm1_psgc":1900000000,"adm2_psgc":1908800000,"adm3_psgc":1908820000,"adm4_psgc":1908820005,"adm4_en":"Lapok","geo_level":"Bgy","len_crs":6003,"area_crs":1714509,"len_km":6,"area_km2":1},"id":1908820005},{"arcs":[[-8,-20,-6,21,22]],"type":"Polygon","properties":{"adm1_psgc":1900000000,"adm2_psgc":1908800000,"adm3_psgc":1908820000,"adm4_psgc":1908820006,"adm4_en":"Malingao","geo_level":"Bgy","len_crs":6214,"area_crs":2076346,"len_km":6,"area_km2":2},"id":1908820006},{"arcs":[[23,24,25,-13]],"type":"Polygon","properties":{"adm1_psgc":1900000000,"adm2_psgc":1908800000,"adm3_psgc":1908820000,"adm4_psgc":1908820007,"adm4_en":"Poblacion","geo_level":"Bgy","len_crs":7240,"area_crs":1585462,"len_km":7,"area_km2":1},"id":1908820007},{"arcs":[[26,27,-17,28,-24,-12]],"type":"Polygon","properties":{"adm1_psgc":1900000000,"adm2_psgc":1908800000,"adm3_psgc":1908820000,"adm4_psgc":1908820008,"adm4_en":"Poblacion I","geo_level":"Bgy","len_crs":7855,"area_crs":2327006,"len_km":7,"area_km2":2},"id":1908820008},{"arcs":[[-26,29,30,-3,-14]],"type":"Polygon","properties":{"adm1_psgc":1900000000,"adm2_psgc":1908800000,"adm3_psgc":1908820000,"adm4_psgc":1908820009,"adm4_en":"Poblacion II","geo_level":"Bgy","len_crs":7419,"area_crs":1547048,"len_km":7,"area_km2":1},"id":1908820009},{"arcs":[[-4,-31,31]],"type":"Polygon","properties":{"adm1_psgc":1900000000,"adm2_psgc":1908800000,"adm3_psgc":1908820000,"adm4_psgc":1908820010,"adm4_en":"Satan","geo_level":"Bgy","len_crs":8005,"area_crs":2090090,"len_km":8,"area_km2":2},"id":1908820010},{"arcs":[[-15,-2,-19,32]],"type":"Polygon","properties":{"adm1_psgc":1900000000,"adm2_psgc":1908800000,"adm3_psgc":1908820000,"adm4_psgc":1908820011,"adm4_en":"Tapikan","geo_level":"Bgy","len_crs":7314,"area_crs":1615579,"len_km":7,"area_km2":1},"id":1908820011},{"arcs":[[-27,-11,33]],"type":"Polygon","properties":{"adm1_psgc":1900000000,"adm2_psgc":1908800000,"adm3_psgc":1908820000,"adm4_psgc":1908820012,"adm4_en":"Timbangan","geo_level":"Bgy","len_crs":11276,"area_crs":4183407,"len_km":11,"area_km2":4},"id":1908820012},{"arcs":[[-9,-23,34]],"type":"Polygon","properties":{"adm1_psgc":1900000000,"adm2_psgc":1908800000,"adm3_psgc":1908820000,"adm4_psgc":1908820013,"adm4_en":"Tina","geo_level":"Bgy","len_crs":12441,"area_crs":7622280,"len_km":12,"area_km2":7},"id":1908820013}]}}}