{"type":"Topology","objects":{"barangays-municity-ph025005000.0.01":{"type":"GeometryCollection","geometries":[{"type":"Polygon","arcs":[[0,1,2,3,4,5]],"properties":{"ADM1_PCODE":"PH020000000","ADM1_EN":"REGION II (CAGAYAN VALLEY)","ADM2_PCODE":"PH025000000","ADM2_EN":"NUEVA VIZCAYA","ADM3_PCODE":"PH025005000","ADM3_EN":"BAYOMBONG (Capital)","ADM4_PCODE":"PH025005001","ADM4_EN":"Bonfal East"}},{"type":"Polygon","arcs":[[-6,6,7,8]],"properties":{"ADM1_PCODE":"PH020000000","ADM1_EN":"REGION II (CAGAYAN VALLEY)","ADM2_PCODE":"PH025000000","ADM2_EN":"NUEVA VIZCAYA","ADM3_PCODE":"PH025005000","ADM3_EN":"BAYOMBONG (Capital)","ADM4_PCODE":"PH025005002","ADM4_EN":"Bonfal Proper"}},{"type":"Polygon","arcs":[[-5,9,10,11,-7]],"properties":{"ADM1_PCODE":"PH020000000","ADM1_EN":"REGION II (CAGAYAN VALLEY)","ADM2_PCODE":"PH025000000","ADM2_EN":"NUEVA VIZCAYA","ADM3_PCODE":"PH025005000","ADM3_EN":"BAYOMBONG (Capital)","ADM4_PCODE":"PH025005003","ADM4_EN":"Bonfal West"}},{"type":"Polygon","arcs":[[12,13,14]],"properties":{"ADM1_PCODE":"PH020000000","ADM1_EN":"REGION II (CAGAYAN VALLEY)","ADM2_PCODE":"PH025000000","ADM2_EN":"NUEVA VIZCAYA","ADM3_PCODE":"PH025005000","ADM3_EN":"BAYOMBONG (Capital)","ADM4_PCODE":"PH025005004","ADM4_EN":"Buenavista (Vista Hills)"}},{"type":"Polygon","arcs":[[15,16,-15,17,18]],"properties":{"ADM1_PCODE":"PH020000000","ADM1_EN":"REGION II (CAGAYAN VALLEY)","ADM2_PCODE":"PH025000000","ADM2_EN":"NUEVA VIZCAYA","ADM3_PCODE":"PH025005000","ADM3_EN":"BAYOMBONG (Capital)","ADM4_PCODE":"PH025005005","ADM4_EN":"Busilac"}},{"type":"Polygon","arcs":[[-8,-12,19,20,21]],"properties":{"ADM1_PCODE":"PH020000000","ADM1_EN":"REGION II (CAGAYAN VALLEY)","ADM2_PCODE":"PH025000000","ADM2_EN":"NUEVA VIZCAYA","ADM3_PCODE":"PH025005000","ADM3_EN":"BAYOMBONG (Capital)","ADM4_PCODE":"PH025005006","ADM4_EN":"Casat"}},{"type":"Polygon","arcs":[[-11,22,23,24,25,-20]],"properties":{"ADM1_PCODE":"PH020000000","ADM1_EN":"REGION II (CAGAYAN VALLEY)","ADM2_PCODE":"PH025000000","ADM2_EN":"NUEVA VIZCAYA","ADM3_PCODE":"PH025005000","ADM3_EN":"BAYOMBONG (Capital)","ADM4_PCODE":"PH025005008","ADM4_EN":"La Torre North"}},{"type":"Polygon","arcs":[[26,27,-13,-17,28]],"properties":{"ADM1_PCODE":"PH020000000","ADM1_EN":"REGION II (CAGAYAN VALLEY)","ADM2_PCODE":"PH025000000","ADM2_EN":"NUEVA VIZCAYA","ADM3_PCODE":"PH025005000","ADM3_EN":"BAYOMBONG (Capital)","ADM4_PCODE":"PH025005009","ADM4_EN":"Magapuy"}},{"type":"Polygon","arcs":[[29,30,31,32,-19,33,34]],"properties":{"ADM1_PCODE":"PH020000000","ADM1_EN":"REGION II (CAGAYAN VALLEY)","ADM2_PCODE":"PH025000000","ADM2_EN":"NUEVA VIZCAYA","ADM3_PCODE":"PH025005000","ADM3_EN":"BAYOMBONG (Capital)","ADM4_PCODE":"PH025005010","ADM4_EN":"Magsaysay"}},{"type":"Polygon","arcs":[[35,-35,36,37]],"properties":{"ADM1_PCODE":"PH020000000","ADM1_EN":"REGION II (CAGAYAN VALLEY)","ADM2_PCODE":"PH025000000","ADM2_EN":"NUEVA VIZCAYA","ADM3_PCODE":"PH025005000","ADM3_EN":"BAYOMBONG (Capital)","ADM4_PCODE":"PH025005011","ADM4_EN":"Masoc"}},{"type":"Polygon","arcs":[[-3,38,-29,-16,-33,39,40,41,42,43]],"properties":{"ADM1_PCODE":"PH020000000","ADM1_EN":"REGION II (CAGAYAN VALLEY)","ADM2_PCODE":"PH025000000","ADM2_EN":"NUEVA VIZCAYA","ADM3_PCODE":"PH025005000","ADM3_EN":"BAYOMBONG (Capital)","ADM4_PCODE":"PH025005012","ADM4_EN":"Paitan"}},{"type":"Polygon","arcs":[[44,45,46,47,48]],"properties":{"ADM1_PCODE":"PH020000000","ADM1_EN":"REGION II (CAGAYAN VALLEY)","ADM2_PCODE":"PH025000000","ADM2_EN":"NUEVA VIZCAYA","ADM3_PCODE":"PH025005000","ADM3_EN":"BAYOMBONG (Capital)","ADM4_PCODE":"PH025005014","ADM4_EN":"Don Domingo Maddela Pob. (District I)"}},{"type":"Polygon","arcs":[[49,50,51,-46]],"properties":{"ADM1_PCODE":"PH020000000","ADM1_EN":"REGION II (CAGAYAN VALLEY)","ADM2_PCODE":"PH025000000","ADM2_EN":"NUEVA VIZCAYA","ADM3_PCODE":"PH025005000","ADM3_EN":"BAYOMBONG (Capital)","ADM4_PCODE":"PH025005015","ADM4_EN":"Don Tomas Maddela Pob. (District II)"}},{"type":"Polygon","arcs":[[52,-47,-52,53,-31,54,55]],"properties":{"ADM1_PCODE":"PH020000000","ADM1_EN":"REGION II (CAGAYAN VALLEY)","ADM2_PCODE":"PH025000000","ADM2_EN":"NUEVA VIZCAYA","ADM3_PCODE":"PH025005000","ADM3_EN":"BAYOMBONG (Capital)","ADM4_PCODE":"PH025005016","ADM4_EN":"District III Pob. (Don M. Perez)"}},{"type":"Polygon","arcs":[[-43,56,-49,57,58]],"properties":{"ADM1_PCODE":"PH020000000","ADM1_EN":"REGION II (CAGAYAN VALLEY)","ADM2_PCODE":"PH025000000","ADM2_EN":"NUEVA VIZCAYA","ADM3_PCODE":"PH025005000","ADM3_EN":"BAYOMBONG (Capital)","ADM4_PCODE":"PH025005017","ADM4_EN":"District IV (Pob.)"}},{"type":"Polygon","arcs":[[59,-27,-39,-2]],"properties":{"ADM1_PCODE":"PH020000000","ADM1_EN":"REGION II (CAGAYAN VALLEY)","ADM2_PCODE":"PH025000000","ADM2_EN":"NUEVA VIZCAYA","ADM3_PCODE":"PH025005000","ADM3_EN":"BAYOMBONG (Capital)","ADM4_PCODE":"PH025005019","ADM4_EN":"Bansing"}},{"type":"Polygon","arcs":[[-21,-26,60,61]],"properties":{"ADM1_PCODE":"PH020000000","ADM1_EN":"REGION II (CAGAYAN VALLEY)","ADM2_PCODE":"PH025000000","ADM2_EN":"NUEVA VIZCAYA","ADM3_PCODE":"PH025005000","ADM3_EN":"BAYOMBONG (Capital)","ADM4_PCODE":"PH025005020","ADM4_EN":"Cabuaan"}},{"type":"Polygon","arcs":[[-42,62,-45,-57]],"properties":{"ADM1_PCODE":"PH020000000","ADM1_EN":"REGION II (CAGAYAN VALLEY)","ADM2_PCODE":"PH025000000","ADM2_EN":"NUEVA VIZCAYA","ADM3_PCODE":"PH025005000","ADM3_EN":"BAYOMBONG (Capital)","ADM4_PCODE":"PH025005021","ADM4_EN":"Don Mariano Marcos"}},{"type":"Polygon","arcs":[[-25,63,-38,64,-61]],"properties":{"ADM1_PCODE":"PH020000000","ADM1_EN":"REGION II (CAGAYAN VALLEY)","ADM2_PCODE":"PH025000000","ADM2_EN":"NUEVA VIZCAYA","ADM3_PCODE":"PH025005000","ADM3_EN":"BAYOMBONG (Capital)","ADM4_PCODE":"PH025005022","ADM4_EN":"Ipil-Cuneg"}},{"type":"Polygon","arcs":[[65,-55,-30,-36,-64,-24]],"properties":{"ADM1_PCODE":"PH020000000","ADM1_EN":"REGION II (CAGAYAN VALLEY)","ADM2_PCODE":"PH025000000","ADM2_EN":"NUEVA VIZCAYA","ADM3_PCODE":"PH025005000","ADM3_EN":"BAYOMBONG (Capital)","ADM4_PCODE":"PH025005023","ADM4_EN":"La Torre South"}},{"type":"Polygon","arcs":[[66,-56,-66,-23]],"properties":{"ADM1_PCODE":"PH020000000","ADM1_EN":"REGION II (CAGAYAN VALLEY)","ADM2_PCODE":"PH025000000","ADM2_EN":"NUEVA VIZCAYA","ADM3_PCODE":"PH025005000","ADM3_EN":"BAYOMBONG (Capital)","ADM4_PCODE":"PH025005024","ADM4_EN":"Luyang"}},{"type":"Polygon","arcs":[[-41,67,-50,-63]],"properties":{"ADM1_PCODE":"PH020000000","ADM1_EN":"REGION II (CAGAYAN VALLEY)","ADM2_PCODE":"PH025000000","ADM2_EN":"NUEVA VIZCAYA","ADM3_PCODE":"PH025005000","ADM3_EN":"BAYOMBONG (Capital)","ADM4_PCODE":"PH025005025","ADM4_EN":"Salvacion"}},{"type":"Polygon","arcs":[[-58,-48,-53,-67,68]],"properties":{"ADM1_PCODE":"PH020000000","ADM1_EN":"REGION II (CAGAYAN VALLEY)","ADM2_PCODE":"PH025000000","ADM2_EN":"NUEVA VIZCAYA","ADM3_PCODE":"PH025005000","ADM3_EN":"BAYOMBONG (Capital)","ADM4_PCODE":"PH025005026","ADM4_EN":"San Nicolas North (Luyang)"}},{"type":"Polygon","arcs":[[-4,-44,-59,-69,-10]],"properties":{"ADM1_PCODE":"PH020000000","ADM1_EN":"REGION II (CAGAYAN VALLEY)","ADM2_PCODE":"PH025000000","ADM2_EN":"NUEVA VIZCAYA","ADM3_PCODE":"PH025005000","ADM3_EN":"BAYOMBONG (Capital)","ADM4_PCODE":"PH025005027","ADM4_EN":"Santa Rosa"}},{"type":"Polygon","arcs":[[-51,-68,-40,-32,-54]],"properties":{"ADM1_PCODE":"PH020000000","ADM1_EN":"REGION II (CAGAYAN VALLEY)","ADM2_PCODE":"PH025000000","ADM2_EN":"NUEVA VIZCAYA","ADM3_PCODE":"PH025005000","ADM3_EN":"BAYOMBONG (Capital)","ADM4_PCODE":"PH025005028","ADM4_EN":"Vista Alegre (B. Baringin)"}}]}},"arcs":[[[121.19292619100008,16.486917050000045],[121.2322888010001,16.45359225800007],[121.2348447170001,16.44236892500004],[121.21373362700001,16.428763899000046]],[[121.21373362700001,16.428763899000046],[121.19138790000011,16.464208892000045],[121.17944799200006,16.475898263000033]],[[121.17944799200006,16.475898263000033],[121.17721161100008,16.479856424000047]],[[121.17721161100008,16.479856424000047],[121.16967403700005,16.494506500000057]],[[121.16967403700005,16.494506500000057],[121.17593115800003,16.498294530000067]],[[121.17593115800003,16.498294530000067],[121.19292619100008,16.486917050000045]],[[121.17593115800003,16.498294530000067],[121.15814450900007,16.51082309700007]],[[121.15814450900007,16.51082309700007],[121.16229198700012,16.51522691200006]],[[121.16229198700012,16.51522691200006],[121.19044243500002,16.504279551000025],[121.19292619100008,16.486917050000045]],[[121.16967403700005,16.494506500000057],[121.1574500270001,16.494903710000074]],[[121.1574500270001,16.494903710000074],[121.15492560000007,16.507051990000036]],[[121.15492560000007,16.507051990000036],[121.15814450900007,16.51082309700007]],[[121.11226702200008,16.454457595000065],[121.11129215200003,16.432976042000064]],[[121.11129215200003,16.432976042000064],[121.0760806940001,16.440925437000033],[121.071164672,16.461770062000028]],[[121.071164672,16.461770062000028],[121.11226702200008,16.454457595000065]],[[121.1258607310001,16.47210961600007],[121.12472599700004,16.470946514000048]],[[121.12472599700004,16.470946514000048],[121.11226702200008,16.454457595000065]],[[121.071164672,16.461770062000028],[121.07201009900007,16.48373352400006]],[[121.07201009900007,16.48373352400006],[121.10002107900004,16.485936711000022],[121.1258607310001,16.47210961600007]],[[121.15492560000007,16.507051990000036],[121.11669351900002,16.528317999000024]],[[121.11669351900002,16.528317999000024],[121.1294613660001,16.53673925100003]],[[121.1294613660001,16.53673925100003],[121.16229198700012,16.51522691200006]],[[121.1574500270001,16.494903710000074],[121.14277510200009,16.495506007000074]],[[121.14277510200009,16.495506007000074],[121.11611339500007,16.513586831000055]],[[121.11611339500007,16.513586831000055],[121.1096930870001,16.521748781000042]],[[121.1096930870001,16.521748781000042],[121.11669351900002,16.528317999000024]],[[121.1416367920001,16.454737384000055],[121.17382474800002,16.442460338000046],[121.18043867800009,16.433465841000043]],[[121.18043867800009,16.433465841000043],[121.142299696,16.43592933000002],[121.11129215200003,16.432976042000064]],[[121.12472599700004,16.470946514000048],[121.1416367920001,16.454737384000055]],[[121.1297621330001,16.491699063000056],[121.13921531200003,16.48709106700005]],[[121.13921531200003,16.48709106700005],[121.13778625600003,16.482214794000072]],[[121.13778625600003,16.482214794000072],[121.13811585400003,16.47318761300005]],[[121.13811585400003,16.47318761300005],[121.1258607310001,16.47210961600007]],[[121.07201009900007,16.48373352400006],[121.08950480600004,16.503890201000047]],[[121.08950480600004,16.503890201000047],[121.09774918300002,16.49614312700004],[121.1297621330001,16.491699063000056]],[[121.11716084000011,16.508282165000026],[121.1297621330001,16.491699063000056]],[[121.08950480600004,16.503890201000047],[121.09523099400008,16.51032389900007]],[[121.09523099400008,16.51032389900007],[121.11716084000011,16.508282165000026]],[[121.17944799200006,16.475898263000033],[121.15951076300007,16.45936808500005],[121.1416367920001,16.454737384000055]],[[121.13811585400003,16.47318761300005],[121.15158977300007,16.472800439000025]],[[121.15158977300007,16.472800439000025],[121.16061023000009,16.47344872700006]],[[121.16061023000009,16.47344872700006],[121.16394427900002,16.475986309000064]],[[121.16394427900002,16.475986309000064],[121.1707235130001,16.47719027100004]],[[121.1707235130001,16.47719027100004],[121.17721161100008,16.479856424000047]],[[121.15444512600004,16.485328981000066],[121.15014100700012,16.48286512900006]],[[121.15014100700012,16.48286512900006],[121.14779074700004,16.484178849000045]],[[121.14779074700004,16.484178849000045],[121.14917161500011,16.48483727400003]],[[121.14917161500011,16.48483727400003],[121.15318140800002,16.486243441000056]],[[121.15318140800002,16.486243441000056],[121.15444512600004,16.485328981000066]],[[121.15014100700012,16.48286512900006],[121.14654498300001,16.478537264000067]],[[121.14654498300001,16.478537264000067],[121.14271833200007,16.477362914000025]],[[121.14271833200007,16.477362914000025],[121.14779074700004,16.484178849000045]],[[121.14645205800002,16.487277810000023],[121.14917161500011,16.48483727400003]],[[121.14271833200007,16.477362914000025],[121.13778625600003,16.482214794000072]],[[121.13921531200003,16.48709106700005],[121.14149093500009,16.490476803000035]],[[121.14149093500009,16.490476803000035],[121.14645205800002,16.487277810000023]],[[121.16394427900002,16.475986309000064],[121.15444512600004,16.485328981000066]],[[121.15318140800002,16.486243441000056],[121.1582885900001,16.49024628600006]],[[121.1582885900001,16.49024628600006],[121.1707235130001,16.47719027100004]],[[121.21373362700001,16.428763899000046],[121.18043867800009,16.433465841000043]],[[121.1096930870001,16.521748781000042],[121.09566999300012,16.537099315000034]],[[121.09566999300012,16.537099315000034],[121.12165396900002,16.552472375000036],[121.1294613660001,16.53673925100003]],[[121.16061023000009,16.47344872700006],[121.15014100700012,16.48286512900006]],[[121.11611339500007,16.513586831000055],[121.11716084000011,16.508282165000026]],[[121.09523099400008,16.51032389900007],[121.09566999300012,16.537099315000034]],[[121.14277510200009,16.495506007000074],[121.14149093500009,16.490476803000035]],[[121.1574500270001,16.494903710000074],[121.14645205800002,16.487277810000023]],[[121.15158977300007,16.472800439000025],[121.14654498300001,16.478537264000067]],[[121.1574500270001,16.494903710000074],[121.1582885900001,16.49024628600006]]],"bbox":[121.071164672,16.428763899000046,121.2348447170001,16.552472375000036]}
