{"type":"Topology","objects":{"barangays-municity-1081-banisilan.0.1":{"type":"GeometryCollection","geometries":[{"type":"Polygon","arcs":[[0,1,2,3]],"properties":{"ID_0":177,"ISO":"PHL","NAME_0":"Philippines","ID_1":53,"NAME_1":"North Cotabato","ID_2":1081,"NAME_2":"Banisilan","ID_3":28263,"NAME_3":"Banisilan Poblacio","NL_NAME_3":null,"VARNAME_3":null,"TYPE_3":"Barangay","ENGTYPE_3":"Village","PROVINCE":"North Cotabato","REGION":"SOCCSKSARGEN (Region XII)"}},{"type":"Polygon","arcs":[[4,5,6,7]],"properties":{"ID_0":177,"ISO":"PHL","NAME_0":"Philippines","ID_1":53,"NAME_1":"North Cotabato","ID_2":1081,"NAME_2":"Banisilan","ID_3":28264,"NAME_3":"Busaon","NL_NAME_3":null,"VARNAME_3":null,"TYPE_3":"Barangay","ENGTYPE_3":"Village","PROVINCE":"North Cotabato","REGION":"SOCCSKSARGEN (Region XII)"}},{"type":"Polygon","arcs":[[8,9,10,11,12]],"properties":{"ID_0":177,"ISO":"PHL","NAME_0":"Philippines","ID_1":53,"NAME_1":"North Cotabato","ID_2":1081,"NAME_2":"Banisilan","ID_3":28265,"NAME_3":"Capayangan","NL_NAME_3":null,"VARNAME_3":null,"TYPE_3":"Barangay","ENGTYPE_3":"Village","PROVINCE":"North Cotabato","REGION":"SOCCSKSARGEN (Region XII)"}},{"type":"Polygon","arcs":[[13,14,15,16]],"properties":{"ID_0":177,"ISO":"PHL","NAME_0":"Philippines","ID_1":53,"NAME_1":"North Cotabato","ID_2":1081,"NAME_2":"Banisilan","ID_3":28266,"NAME_3":"Carugmanan","NL_NAME_3":null,"VARNAME_3":null,"TYPE_3":"Barangay","ENGTYPE_3":"Village","PROVINCE":"North Cotabato","REGION":"SOCCSKSARGEN (Region XII)"}},{"type":"Polygon","arcs":[[17,-11,18,19,20]],"properties":{"ID_0":177,"ISO":"PHL","NAME_0":"Philippines","ID_1":53,"NAME_1":"North Cotabato","ID_2":1081,"NAME_2":"Banisilan","ID_3":28267,"NAME_3":"Gastay","NL_NAME_3":null,"VARNAME_3":null,"TYPE_3":"Barangay","ENGTYPE_3":"Village","PROVINCE":"North Cotabato","REGION":"SOCCSKSARGEN (Region XII)"}},{"type":"Polygon","arcs":[[-12,-18,21]],"properties":{"ID_0":177,"ISO":"PHL","NAME_0":"Philippines","ID_1":53,"NAME_1":"North Cotabato","ID_2":1081,"NAME_2":"Banisilan","ID_3":28268,"NAME_3":"Kalawaig","NL_NAME_3":null,"VARNAME_3":null,"TYPE_3":"Barangay","ENGTYPE_3":"Village","PROVINCE":"North Cotabato","REGION":"SOCCSKSARGEN (Region XII)"}},{"type":"Polygon","arcs":[[22,23,24]],"properties":{"ID_0":177,"ISO":"PHL","NAME_0":"Philippines","ID_1":53,"NAME_1":"North Cotabato","ID_2":1081,"NAME_2":"Banisilan","ID_3":28269,"NAME_3":"Kiaring","NL_NAME_3":null,"VARNAME_3":null,"TYPE_3":"Barangay","ENGTYPE_3":"Village","PROVINCE":"North Cotabato","REGION":"SOCCSKSARGEN (Region XII)"}},{"type":"Polygon","arcs":[[-24,25,26,27,28]],"properties":{"ID_0":177,"ISO":"PHL","NAME_0":"Philippines","ID_1":53,"NAME_1":"North Cotabato","ID_2":1081,"NAME_2":"Banisilan","ID_3":28270,"NAME_3":"Malagap","NL_NAME_3":null,"VARNAME_3":null,"TYPE_3":"Barangay","ENGTYPE_3":"Village","PROVINCE":"North Cotabato","REGION":"SOCCSKSARGEN (Region XII)"}},{"type":"Polygon","arcs":[[-10,29,30,31,32,-19]],"properties":{"ID_0":177,"ISO":"PHL","NAME_0":"Philippines","ID_1":53,"NAME_1":"North Cotabato","ID_2":1081,"NAME_2":"Banisilan","ID_3":28271,"NAME_3":"Malinao","NL_NAME_3":null,"VARNAME_3":null,"TYPE_3":"Barangay","ENGTYPE_3":"Village","PROVINCE":"North Cotabato","REGION":"SOCCSKSARGEN (Region XII)"}},{"type":"Polygon","arcs":[[33,34,35,-30,-9]],"properties":{"ID_0":177,"ISO":"PHL","NAME_0":"Philippines","ID_1":53,"NAME_1":"North Cotabato","ID_2":1081,"NAME_2":"Banisilan","ID_3":28272,"NAME_3":"Miguel Macasarte","NL_NAME_3":null,"VARNAME_3":null,"TYPE_3":"Barangay","ENGTYPE_3":"Village","PROVINCE":"North Cotabato","REGION":"SOCCSKSARGEN (Region XII)"}},{"type":"Polygon","arcs":[[36,37,38,39,-2]],"properties":{"ID_0":177,"ISO":"PHL","NAME_0":"Philippines","ID_1":53,"NAME_1":"North Cotabato","ID_2":1081,"NAME_2":"Banisilan","ID_3":28273,"NAME_3":"Pantar","NL_NAME_3":null,"VARNAME_3":null,"TYPE_3":"Barangay","ENGTYPE_3":"Village","PROVINCE":"North Cotabato","REGION":"SOCCSKSARGEN (Region XII)"}},{"type":"Polygon","arcs":[[-20,-33,40,41]],"properties":{"ID_0":177,"ISO":"PHL","NAME_0":"Philippines","ID_1":53,"NAME_1":"North Cotabato","ID_2":1081,"NAME_2":"Banisilan","ID_3":28274,"NAME_3":"Paradise","NL_NAME_3":null,"VARNAME_3":null,"TYPE_3":"Barangay","ENGTYPE_3":"Village","PROVINCE":"North Cotabato","REGION":"SOCCSKSARGEN (Region XII)"}},{"type":"Polygon","arcs":[[42,-8,-15,43,-35]],"properties":{"ID_0":177,"ISO":"PHL","NAME_0":"Philippines","ID_1":53,"NAME_1":"North Cotabato","ID_2":1081,"NAME_2":"Banisilan","ID_3":28275,"NAME_3":"Pinamulaan","NL_NAME_3":null,"VARNAME_3":null,"TYPE_3":"Barangay","ENGTYPE_3":"Village","PROVINCE":"North Cotabato","REGION":"SOCCSKSARGEN (Region XII)"}},{"type":"Polygon","arcs":[[-17,44,-37,-1,45]],"properties":{"ID_0":177,"ISO":"PHL","NAME_0":"Philippines","ID_1":53,"NAME_1":"North Cotabato","ID_2":1081,"NAME_2":"Banisilan","ID_3":28276,"NAME_3":"Poblacion II","NL_NAME_3":null,"VARNAME_3":null,"TYPE_3":"Barangay","ENGTYPE_3":"Village","PROVINCE":"North Cotabato","REGION":"SOCCSKSARGEN (Region XII)"}},{"type":"Polygon","arcs":[[-27,46]],"properties":{"ID_0":177,"ISO":"PHL","NAME_0":"Philippines","ID_1":53,"NAME_1":"North Cotabato","ID_2":1081,"NAME_2":"Banisilan","ID_3":28277,"NAME_3":"Puting-Bato","NL_NAME_3":null,"VARNAME_3":null,"TYPE_3":"Barangay","ENGTYPE_3":"Village","PROVINCE":"North Cotabato","REGION":"SOCCSKSARGEN (Region XII)"}},{"type":"Polygon","arcs":[[47,-25,-29,48,49]],"properties":{"ID_0":177,"ISO":"PHL","NAME_0":"Philippines","ID_1":53,"NAME_1":"North Cotabato","ID_2":1081,"NAME_2":"Banisilan","ID_3":28278,"NAME_3":"Solama","NL_NAME_3":null,"VARNAME_3":null,"TYPE_3":"Barangay","ENGTYPE_3":"Village","PROVINCE":"North Cotabato","REGION":"SOCCSKSARGEN (Region XII)"}},{"type":"Polygon","arcs":[[-7,50,-38,-45,-16]],"properties":{"ID_0":177,"ISO":"PHL","NAME_0":"Philippines","ID_1":53,"NAME_1":"North Cotabato","ID_2":1081,"NAME_2":"Banisilan","ID_3":28279,"NAME_3":"Thailand","NL_NAME_3":null,"VARNAME_3":null,"TYPE_3":"Barangay","ENGTYPE_3":"Village","PROVINCE":"North Cotabato","REGION":"SOCCSKSARGEN (Region XII)"}},{"type":"Polygon","arcs":[[-6,51,-50,52,-39,-51]],"properties":{"ID_0":177,"ISO":"PHL","NAME_0":"Philippines","ID_1":53,"NAME_1":"North Cotabato","ID_2":1081,"NAME_2":"Banisilan","ID_3":28280,"NAME_3":"Tinimbacan","NL_NAME_3":null,"VARNAME_3":null,"TYPE_3":"Barangay","ENGTYPE_3":"Village","PROVINCE":"North Cotabato","REGION":"SOCCSKSARGEN (Region XII)"}},{"type":"Polygon","arcs":[[-31,-36,-44,-14,-46,53]],"properties":{"ID_0":177,"ISO":"PHL","NAME_0":"Philippines","ID_1":53,"NAME_1":"North Cotabato","ID_2":1081,"NAME_2":"Banisilan","ID_3":28281,"NAME_3":"Tumbao-Camalig","NL_NAME_3":null,"VARNAME_3":null,"TYPE_3":"Barangay","ENGTYPE_3":"Village","PROVINCE":"North Cotabato","REGION":"SOCCSKSARGEN (Region XII)"}},{"type":"Polygon","arcs":[[-32,-54,-4,54,-41]],"properties":{"ID_0":177,"ISO":"PHL","NAME_0":"Philippines","ID_1":53,"NAME_1":"North Cotabato","ID_2":1081,"NAME_2":"Banisilan","ID_3":28282,"NAME_3":"Wadya","NL_NAME_3":null,"VARNAME_3":null,"TYPE_3":"Barangay","ENGTYPE_3":"Village","PROVINCE":"North Cotabato","REGION":"SOCCSKSARGEN (Region XII)"}}]}},"arcs":[[[124.70117950439453,7.533070087432975],[124.69859313964866,7.491720199584961]],[[124.69859313964866,7.491720199584961],[124.67449951171875,7.486519813537654]],[[124.67449951171875,7.486519813537654],[124.67180633544922,7.50738000869751],[124.66401672363281,7.520319938659725],[124.660400390625,7.535950183868408]],[[124.660400390625,7.535950183868408],[124.70117950439453,7.533070087432975]],[[124.79045867919922,7.492609977722168],[124.7882308959961,7.480229854583797],[124.773681640625,7.469699859619084]],[[124.773681640625,7.469699859619084],[124.75523376464844,7.477119922638053]],[[124.75523376464844,7.477119922638053],[124.78080749511741,7.495979785919303]],[[124.78080749511741,7.495979785919303],[124.79045867919922,7.492609977722168]],[[124.81226348876953,7.57411003112793],[124.8055191040039,7.571280002594108],[124.73986053466808,7.567299842834473]],[[124.73986053466808,7.567299842834473],[124.73977661132812,7.599370002746696]],[[124.73977661132812,7.599370002746696],[124.73989868164062,7.603769779205379]],[[124.73989868164062,7.603769779205379],[124.7930908203125,7.602660179138297],[124.79910278320312,7.605549812316895]],[[124.79910278320312,7.605549812316895],[124.81503295898438,7.595819950103703],[124.81226348876953,7.57411003112793]],[[124.74285888671886,7.531449794769344],[124.75469970703136,7.530409812927189]],[[124.75469970703136,7.530409812927189],[124.76793670654297,7.523690223693904],[124.78080749511741,7.495979785919303]],[[124.78080749511741,7.495979785919303],[124.74754333496094,7.49623012542736]],[[124.74754333496094,7.49623012542736],[124.7438430786134,7.506110191345272],[124.74285888671886,7.531449794769344]],[[124.74372863769531,7.621809959411621],[124.73989868164062,7.603769779205379]],[[124.73977661132812,7.599370002746696],[124.69992065429688,7.60090017318737]],[[124.69992065429688,7.60090017318737],[124.70025634765625,7.639830112457275]],[[124.70025634765625,7.639830112457275],[124.73475646972656,7.627520084381104],[124.74372863769531,7.621809959411621]],[[124.74372863769531,7.621809959411621],[124.75862121582031,7.617149829864445],[124.77512359619152,7.619740009307861],[124.78605651855469,7.608489990234375],[124.79910278320312,7.605549812316895]],[[124.75308990478516,7.39621019363409],[124.74817657470703,7.387469768524227],[124.73341369628906,7.382440090179443],[124.72440338134777,7.373509883880558],[124.69439697265648,7.353769779205436]],[[124.69439697265648,7.353769779205436],[124.68740844726574,7.369530200958366],[124.69136047363293,7.389420032501221],[124.71096801757812,7.407330036163387],[124.71803283691406,7.409900188446045]],[[124.71803283691406,7.409900188446045],[124.75308990478516,7.39621019363409]],[[124.69439697265648,7.353769779205436],[124.6841812133789,7.347010135650692]],[[124.6841812133789,7.347010135650692],[124.6759490966798,7.359539985656738],[124.66220855712902,7.36769008636486],[124.64942932128918,7.36775016784668]],[[124.64942932128918,7.36775016784668],[124.64794158935547,7.396430015564022],[124.66626739501953,7.410160064697379],[124.67643737792969,7.42746019363409]],[[124.67643737792969,7.42746019363409],[124.71803283691406,7.409900188446045]],[[124.73986053466808,7.567299842834473],[124.7451629638673,7.554289817810059]],[[124.7451629638673,7.554289817810059],[124.73323822021484,7.548689842224235],[124.71460723876953,7.551099777221737],[124.7049026489259,7.556930065155086]],[[124.7049026489259,7.556930065155086],[124.70025634765625,7.576159954071159]],[[124.70025634765625,7.576159954071159],[124.69992065429688,7.60090017318737]],[[124.81226348876953,7.57411003112793],[124.82501220703125,7.558340072631893],[124.8227996826173,7.546979904174748]],[[124.8227996826173,7.546979904174748],[124.79769897460938,7.549530029296875],[124.76059722900402,7.548830032348633],[124.7511978149414,7.545599937439022]],[[124.7511978149414,7.545599937439022],[124.7451629638673,7.554289817810059]],[[124.69859313964866,7.491720199584961],[124.73204040527355,7.495240211486816]],[[124.73204040527355,7.495240211486816],[124.7168197631836,7.47186994552618],[124.71833801269531,7.463379859924316]],[[124.71833801269531,7.463379859924316],[124.70098114013672,7.46455001831049],[124.68025207519531,7.461410045623836]],[[124.68025207519531,7.461410045623836],[124.67449951171875,7.486519813537654]],[[124.70025634765625,7.576159954071159],[124.65624237060547,7.577859878540039]],[[124.65624237060547,7.577859878540039],[124.65373229980469,7.588200092315788],[124.64356231689453,7.601339817047176],[124.64862060546898,7.613080024719295],[124.67163848876953,7.62404012680048],[124.6800765991211,7.633110046386719],[124.70025634765625,7.639830112457275]],[[124.8227996826173,7.546979904174748],[124.82507324218761,7.541480064392033],[124.81067657470703,7.530560016632137],[124.80059814453125,7.505350112915039],[124.79045867919922,7.492609977722168]],[[124.75469970703136,7.530409812927189],[124.7511978149414,7.545599937439022]],[[124.74754333496094,7.49623012542736],[124.73204040527355,7.495240211486816]],[[124.70117950439453,7.533070087432975],[124.74285888671886,7.531449794769344]],[[124.6841812133789,7.347010135650692],[124.6305923461914,7.311890125274715],[124.64409637451183,7.338590145111027],[124.63780212402355,7.352169990539664],[124.64942932128918,7.36775016784668]],[[124.76373291015625,7.442100048065242],[124.76490020751953,7.426479816436881],[124.75308990478516,7.39621019363409]],[[124.67643737792969,7.42746019363409],[124.68425750732422,7.441289901733512]],[[124.68425750732422,7.441289901733512],[124.73462677001953,7.435359954833928],[124.76373291015625,7.442100048065242]],[[124.75523376464844,7.477119922638053],[124.73625183105469,7.463160037994442],[124.71833801269531,7.463379859924316]],[[124.773681640625,7.469699859619084],[124.7689208984375,7.464990139007568],[124.76373291015625,7.442100048065242]],[[124.68425750732422,7.441289901733512],[124.68025207519531,7.461410045623836]],[[124.70117950439453,7.533070087432975],[124.7049026489259,7.556930065155086]],[[124.660400390625,7.535950183868408],[124.65284729003918,7.565859794616699],[124.65624237060547,7.577859878540039]]],"bbox":[124.6305923461914,7.311890125274715,124.82507324218761,7.639830112457275]}
